sphericart/torch/__init__.py
sphericart/torch/e3nn.py
sphericart/torch/metatensor.py
sphericart/torch/spherical_hamonics.py
sphericart/torch/torch-2.4/_build_torch_version.py
sphericart/torch/torch-2.4/lib/libsphericart_torch.so
sphericart/torch/torch-2.4/lib/libsphericart_torch_cuda_stream.so
sphericart/torch/torch-2.5/_build_torch_version.py
sphericart/torch/torch-2.5/lib/libsphericart_torch.so
sphericart/torch/torch-2.5/lib/libsphericart_torch_cuda_stream.so
sphericart/torch/torch-2.6/_build_torch_version.py
sphericart/torch/torch-2.6/lib/libsphericart_torch.so
sphericart/torch/torch-2.6/lib/libsphericart_torch_cuda_stream.so
sphericart/torch/torch-2.7/_build_torch_version.py
sphericart/torch/torch-2.7/lib/libsphericart_torch.so
sphericart/torch/torch-2.7/lib/libsphericart_torch_cuda_stream.so
sphericart/torch/torch-2.8/_build_torch_version.py
sphericart/torch/torch-2.8/lib/libsphericart_torch.so
sphericart/torch/torch-2.8/lib/libsphericart_torch_cuda_stream.so
sphericart/torch/torch-2.9/_build_torch_version.py
sphericart/torch/torch-2.9/lib/libsphericart_torch.so
sphericart/torch/torch-2.9/lib/libsphericart_torch_cuda_stream.so
sphericart_torch-1.0.5.dist-info/sboms/auditwheel.cdx.json
sphericart_torch.libs/libgomp-a49a47f9.so.1.0.0
sphericart_torch-1.0.5.dist-info/METADATA
sphericart_torch-1.0.5.dist-info/WHEEL
sphericart_torch-1.0.5.dist-info/top_level.txt
sphericart_torch-1.0.5.dist-info/RECORD
